astronomical_matching/__init__.py
astronomical_matching/chainbreaker.py
astronomical_matching/constants.py
astronomical_matching/cop_kmeans.py
astronomical_matching/dirilp.py
astronomical_matching/kmeans.py
astronomical_matching/miqcp.py
astronomical_matching/simulate.py
astronomical_matching/utils.py
astronomical_matching-0.1.dev0.dist-info/LICENSE
astronomical_matching-0.1.dev0.dist-info/METADATA
astronomical_matching-0.1.dev0.dist-info/WHEEL
astronomical_matching-0.1.dev0.dist-info/top_level.txt
astronomical_matching-0.1.dev0.dist-info/RECORD
