Metadata-Version: 2.1
Name: astronomical-matching
Version: 0.1.dev0
Summary: Astronomical Cross Matching: Collection of algorithms to solve the astronomical cross matching problem.
Maintainer-email: Jacob Feitelberg <jef2182@columbia.edu>
License: BSD 3-Clause License
Keywords: Bayes factor,MIQCP,COP-KMeans,Cross-Matching
Classifier: Operating System :: Microsoft :: Windows
Classifier: Operating System :: Unix
Classifier: Operating System :: MacOS
Classifier: Programming Language :: Python :: 3 :: Only
Classifier: Programming Language :: Python :: 3.11
Classifier: Natural Language :: English
Classifier: License :: OSI Approved :: BSD License
Classifier: Intended Audience :: Science/Research
Classifier: Intended Audience :: Developers
Classifier: Topic :: Software Development
Classifier: Topic :: Scientific/Engineering
Requires-Python: ~=3.11
License-File: LICENSE
Requires-Dist: numpy (>=1.21)
Requires-Dist: scipy (>=1.2.0)
Requires-Dist: pandas
Provides-Extra: build
Requires-Dist: build ; extra == 'build'
Requires-Dist: twine ; extra == 'build'
Provides-Extra: full
Requires-Dist: astronomical-matching[build] ; extra == 'full'
Requires-Dist: astronomical-matching[style] ; extra == 'full'
Requires-Dist: astronomical-matching[test] ; extra == 'full'
Provides-Extra: style
Requires-Dist: bibclean ; extra == 'style'
Requires-Dist: black ; extra == 'style'
Requires-Dist: isort ; extra == 'style'
Requires-Dist: flake8 ; extra == 'style'
Requires-Dist: mypy ; extra == 'style'
Requires-Dist: pydocstyle[toml] ; extra == 'style'
Provides-Extra: test
Requires-Dist: pytest ; extra == 'test'
Requires-Dist: pytest-cov ; extra == 'test'
